IronManFly/__init__.py
IronManFly/algo_engine.py
IronManFly/app.py
IronManFly/microservice.py
IronManFly/sum_test_py.py
IronManFly/sum_test_py2.py
IronManFly/.ipynb_checkpoints/Untitled-checkpoint.ipynb
IronManFly-0.1.1.dist-info/DESCRIPTION.rst
IronManFly-0.1.1.dist-info/METADATA
IronManFly-0.1.1.dist-info/RECORD
IronManFly-0.1.1.dist-info/WHEEL
IronManFly-0.1.1.dist-info/metadata.json
IronManFly-0.1.1.dist-info/top_level.txt
