Metadata-Version: 2.0
Name: IronManFly
Version: 0.1.1
Summary: REST API Frame for wanda machine learning service, made easy.
Home-page: https://github.com/leepand
Author: Li Pandeng
Author-email: pandeng.li@163.com
License: BSD
Platform: UNKNOWN
Requires-Dist: flask
Requires-Dist: flask-profiler
Requires-Dist: importlib
Requires-Dist: paste
Requires-Dist: requests
